fluidize/__init__.py
fluidize/client.py
fluidize/config.py
fluidize/adapters/local/__init__.py
fluidize/adapters/local/adapter.py
fluidize/adapters/local/graph.py
fluidize/adapters/local/projects.py
fluidize/adapters/local/runs.py
fluidize/adapters/local/simulation.py
fluidize/core/__init__.py
fluidize/core/constants.py
fluidize/core/modules/__init__.py
fluidize/core/modules/execute/__init__.py
fluidize/core/modules/execute/docker_client.py
fluidize/core/modules/execute/execution_manager.py
fluidize/core/modules/execute/vm_client.py
fluidize/core/modules/execute/utilities/__init__.py
fluidize/core/modules/execute/utilities/environment_builder.py
fluidize/core/modules/execute/utilities/path_converter.py
fluidize/core/modules/execute/utilities/resource_builder.py
fluidize/core/modules/execute/utilities/universal_builder.py
fluidize/core/modules/execute/utilities/volume_builder.py
fluidize/core/modules/graph/__init__.py
fluidize/core/modules/graph/model.py
fluidize/core/modules/graph/parameters.py
fluidize/core/modules/graph/process.py
fluidize/core/modules/graph/processor.py
fluidize/core/modules/graph/edges/edge.py
fluidize/core/modules/graph/nodes/node.py
fluidize/core/modules/projects/__init__.py
fluidize/core/modules/projects/processor.py
fluidize/core/modules/run/__init__.py
fluidize/core/modules/run/node/__init__.py
fluidize/core/modules/run/node/node_runner.py
fluidize/core/modules/run/node/methods/base/Environment.py
fluidize/core/modules/run/node/methods/base/Execute.py
fluidize/core/modules/run/node/methods/base/__init__.py
fluidize/core/modules/run/node/methods/base/execstrat.py
fluidize/core/modules/run/node/methods/local/Environment.py
fluidize/core/modules/run/node/methods/local/ExecuteNew.py
fluidize/core/modules/run/node/methods/local/execstrat.py
fluidize/core/modules/run/project/__init__.py
fluidize/core/modules/run/project/project_runner.py
fluidize/core/modules/run/project/methods/base.py
fluidize/core/modules/run/project/methods/local.py
fluidize-0.0.5.dist-info/METADATA
fluidize-0.0.5.dist-info/WHEEL
fluidize-0.0.5.dist-info/licenses/LICENSE
fluidize-0.0.5.dist-info/RECORD
