Metadata-Version: 2.4
Name: fluidize
Version: 0.0.5
Summary: Python package for automatic generation of scientific computing software pipelines.
Project-URL: Homepage, https://Fluidize-Inc.github.io/fluidize-python/
Project-URL: Repository, https://github.com/Fluidize-Inc/fluidize-python
Project-URL: Documentation, https://Fluidize-Inc.github.io/fluidize-python/
Author-email: Henry Bae <henry@fluidize.ai>
License-File: LICENSE
Keywords: python
Classifier: Intended Audience :: Developers
Classifier: Programming Language :: Python
Classifier: Programming Language :: Python :: 3
Classifier: Programming Language :: Python :: 3.9
Classifier: Programming Language :: Python :: 3.10
Classifier: Programming Language :: Python :: 3.11
Classifier: Programming Language :: Python :: 3.12
Classifier: Programming Language :: Python :: 3.13
Classifier: Topic :: Software Development :: Libraries :: Python Modules
Requires-Python: <4.0,>=3.9
Requires-Dist: asciitree>=0.3.3
Requires-Dist: docker>=7.1.0
Requires-Dist: fluidize-sdk>=0.7.0
Requires-Dist: jinja2>=3.1.6
Requires-Dist: mlflow>=3.1.4
Requires-Dist: networkx>=3.2.1
Requires-Dist: pydantic>=2.11.7
Requires-Dist: pyyaml>=6.0.2
Requires-Dist: universal-pathlib>=0.2.6
